pypricetrend/__init__.py
pypricetrend/demand_trend.py
pypricetrend/forecast.py
pypricetrend/tests/__init__.py
pypricetrend/tests/test_demand_trend.py
pypricetrend/tests/test_forecast.py
pypricetrend-0.1.0.dist-info/LICENSE
pypricetrend-0.1.0.dist-info/METADATA
pypricetrend-0.1.0.dist-info/WHEEL
pypricetrend-0.1.0.dist-info/top_level.txt
pypricetrend-0.1.0.dist-info/RECORD
