Metadata-Version: 2.1
Name: pypricetrend
Version: 0.1.0
Summary: The `pypricetrend` package provides tools to analyze and forecast product demand based on historical sales data
Home-page: https://github.com/dominicplouffe/pypricetrend
Author: Dominic Plouffe
Author-email: dominic@dplouffe.ca
Classifier: Programming Language :: Python :: 3
Classifier: License :: OSI Approved :: MIT License
Classifier: Operating System :: OS Independent
Requires-Python: >=3.6
License-File: LICENSE
Requires-Dist: numpy
Requires-Dist: pandas
Requires-Dist: scikit-learn
Requires-Dist: matplotlib
